README.md
setup.cfg
setup.py
awtest/__init__.py
awtest.egg-info/PKG-INFO
awtest.egg-info/SOURCES.txt
awtest.egg-info/dependency_links.txt
awtest.egg-info/not-zip-safe
awtest.egg-info/requires.txt
awtest.egg-info/top_level.txt
awtest/cv/__init__.py
awtest/cv/search.py
awtest/cv/search2.py
awtest/cv/sfs.py
awtest/cv/sfs2.py
awtest/cv/utilities.py